aind_data_access_api/__init__.py
aind_data_access_api/credentials.py
aind_data_access_api/document_db.py
aind_data_access_api/document_db_ssh.py
aind_data_access_api/rds_tables.py
aind_data_access_api/secrets.py
aind_data_access_api/utils.py
aind_data_access_api/helpers/__init__.py
aind_data_access_api/helpers/data_schema.py
aind_data_access_api/helpers/docdb.py
aind_data_access_api-1.9.2.dist-info/licenses/LICENSE
aind_data_access_api-1.9.2.dist-info/METADATA
aind_data_access_api-1.9.2.dist-info/WHEEL
aind_data_access_api-1.9.2.dist-info/top_level.txt
aind_data_access_api-1.9.2.dist-info/RECORD
