Metadata-Version: 2.4
Name: aind-data-access-api
Version: 1.9.2
Summary: API to interact with a few AIND databases
Author: Allen Institute for Neural Dynamics
License: MIT
Classifier: Programming Language :: Python :: 3
Requires-Python: >=3.8
License-File: LICENSE
Requires-Dist: requests
Requires-Dist: boto3
Requires-Dist: pydantic<2.12,>=2.0
Requires-Dist: pydantic-settings>=2.0
Provides-Extra: dev
Requires-Dist: black; extra == "dev"
Requires-Dist: coverage; extra == "dev"
Requires-Dist: flake8; extra == "dev"
Requires-Dist: interrogate; extra == "dev"
Requires-Dist: isort; extra == "dev"
Requires-Dist: Sphinx; extra == "dev"
Requires-Dist: furo; extra == "dev"
Requires-Dist: aind-data-access-api[full]; extra == "dev"
Provides-Extra: secrets
Provides-Extra: docdb
Requires-Dist: pymongo==4.3.3; extra == "docdb"
Requires-Dist: sshtunnel; extra == "docdb"
Provides-Extra: rds
Requires-Dist: psycopg2-binary==2.9.5; extra == "rds"
Requires-Dist: pandas<2.2.0,>=2.0.0; extra == "rds"
Requires-Dist: SQLAlchemy==1.4.49; extra == "rds"
Provides-Extra: helpers
Requires-Dist: aind-data-schema<2.0,>=1.1.0; extra == "helpers"
Requires-Dist: pandas; extra == "helpers"
Provides-Extra: full
Requires-Dist: aind-data-access-api[secrets]; extra == "full"
Requires-Dist: aind-data-access-api[docdb]; extra == "full"
Requires-Dist: aind-data-access-api[rds]; extra == "full"
Requires-Dist: aind-data-access-api[helpers]; extra == "full"
Dynamic: license-file
